LICENSE
MANIFEST.in
README.rst
setup.py
django_resumator.egg-info/PKG-INFO
django_resumator.egg-info/SOURCES.txt
django_resumator.egg-info/dependency_links.txt
django_resumator.egg-info/requires.txt
django_resumator.egg-info/top_level.txt
resumator/__init__.py
resumator/admin.py
resumator/models.py
resumator/tests.py
resumator/urls.py
resumator/utils.py
resumator/views.py
resumator/migrations/0001_initial.py
resumator/migrations/0001_initial.pyc
resumator/migrations/__init__.py
resumator/migrations/__init__.pyc
resumator/static/resumator/css/base.css
resumator/static/resumator/css/normalize.css
resumator/static/resumator/css/resumator-education.css
resumator/static/resumator/css/resumator-experience.css
resumator/static/resumator/css/resumator-projects.css
resumator/static/resumator/css/resumator-publications.css
resumator/static/resumator/css/skeleton.css
resumator/templates/admin/base_site.html
resumator/templates/admin/solo/change_form.html
resumator/templates/admin/solo/object_history.html
resumator/templates/resumator/base.html
resumator/templates/resumator/education.html
resumator/templates/resumator/experience.html
resumator/templates/resumator/index.html
resumator/templates/resumator/projects.html
resumator/templates/resumator/publications.html
resumator/templatetags/__init__.py
resumator/templatetags/base_extras.py
resumator/templatetags/experience_extras.py
resumator/templatetags/projects_extras.py