Metadata-Version: 1.1
Name: django-resumator
Version: 1.1.4
Summary: A lightweight Django app to create Web-based resumes.
Home-page: https://github.com/AmmsA/django-resumator
Author: Mustafa S
Author-email: AmmsA@users.noreply.github.com
License: MIT License
Platform: UNKNOWN
Classifier: Environment :: Web Environment
Classifier: Framework :: Django
Classifier: Intended Audience :: Developers
Classifier: License :: OSI Approved :: MIT License
Classifier: Operating System :: OS Independent
Classifier: Programming Language :: Python
Classifier: Programming Language :: Python :: 3
Classifier: Programming Language :: Python :: 3.2
Classifier: Programming Language :: Python :: 3.3
Classifier: Topic :: Internet :: WWW/HTTP
Classifier: Topic :: Internet :: WWW/HTTP :: Dynamic Content
